{"gameId":"oJuYP2_PuFzNHQZPQS","variant":"xiangqi","createdAt":1761038737,"turn":"red","version":8,"players":{"red":{"token":"R_qNunyxIHzeupmyv6fF56KAJ6"},"black":{"token":"B_nCjflw16pgChrWImdlEB9Kpf"}},"board":[["b_R","b_H","b_E","b_A","b_G","b_A","b_E","b_H",null],[null,null,null,null,null,null,null,null,null],[null,"b_C",null,null,null,null,null,"b_C",null],["b_S",null,"b_S",null,null,null,"b_S",null,"b_R"],[null,null,null,null,"b_S",null,null,null,"b_S"],[null,null,null,null,null,null,"r_S",null,null],["r_S",null,"r_S",null,"r_S",null,null,null,"r_S"],[null,"r_C",null,null,"r_E",null,null,null,"r_C"],[null,null,null,null,null,null,null,null,null],["r_R","r_H","r_E","r_A","r_G","r_A",null,"r_H","r_R"]],"moves":[{"from":[7,7],"to":[7,8],"by":"red","cap":null,"ts":1761038825},{"from":[3,8],"to":[4,8],"by":"black","cap":null,"ts":1761038834},{"from":[6,6],"to":[5,6],"by":"red","cap":null,"ts":1761040308},{"from":[3,4],"to":[4,4],"by":"black","cap":null,"ts":1761040334},{"from":[9,6],"to":[7,4],"by":"red","cap":null,"ts":1761040346},{"from":[0,8],"to":[3,8],"by":"black","cap":null,"ts":1761041841}],"result":{"winner":"black","reason":"resignation"}}